MANIFEST.in
README.rst
setup.cfg
setup.py
crosscompute_integer/__init__.py
crosscompute_integer/type.jinja2
crosscompute_integer.egg-info/PKG-INFO
crosscompute_integer.egg-info/SOURCES.txt
crosscompute_integer.egg-info/dependency_links.txt
crosscompute_integer.egg-info/entry_points.txt
crosscompute_integer.egg-info/not-zip-safe
crosscompute_integer.egg-info/requires.txt
crosscompute_integer.egg-info/top_level.txt