Metadata-Version: 1.1
Name: crosscompute-integer
Version: 0.7.3
Summary: Integer data type plugin for CrossCompute
Home-page: https://crosscompute.com/docs
Author: CrossCompute Inc
Author-email: support@crosscompute.com
License: UNKNOWN
Keywords: web pyramid pylons crosscompute
Platform: UNKNOWN
Classifier: Programming Language :: Python
Classifier: Framework :: Pyramid
Classifier: Topic :: Internet :: WWW/HTTP :: WSGI :: Application
Classifier: License :: OSI Approved :: MIT License
